gottcha/__init__.py
gottcha/scripts/__init__.py
gottcha/scripts/cmd.py
gottcha/scripts/gottcha2.py
gottcha/scripts/pull_database.py
gottcha/scripts/taxonomy.py
GOTTCHA2-2.1.8.55.dist-info/LICENSE
GOTTCHA2-2.1.8.55.dist-info/METADATA
GOTTCHA2-2.1.8.55.dist-info/WHEEL
GOTTCHA2-2.1.8.55.dist-info/entry_points.txt
GOTTCHA2-2.1.8.55.dist-info/top_level.txt
GOTTCHA2-2.1.8.55.dist-info/RECORD
