Metadata-Version: 2.1
Name: GOTTCHA2
Version: 2.1.8.55
Summary: Genomic Origin Through Taxonomic CHAllenge (GOTTCHA) v2
Author-email: Po-E Li <po-e@lanl.gov>
License: Copyright (2019). TRIAD National Security, LLC. This material was produced under U.S. Government contract 
Project-URL: Homepage, https://github.com/poeli/GOTTCHA2/tree/master
Keywords: bioinformatics,taxonomy,profiler
Classifier: Programming Language :: Python :: 3
Classifier: License :: OSI Approved :: BSD License
Classifier: Operating System :: OS Independent
Classifier: Topic :: Scientific/Engineering :: Bio-Informatics
License-File: LICENSE
Requires-Dist: numpy >=1.26.2
Requires-Dist: pandas >=2.1.1
Requires-Dist: requests >=2.31.0
Requires-Dist: tqdm >=4.66.1
